AUTHORS.rst
CONTRIBUTING.rst
HISTORY.rst
LICENSE
MANIFEST.in
README.rst
setup.cfg
setup.py
docs/Makefile
docs/authors.rst
docs/conf.py
docs/contributing.rst
docs/history.rst
docs/index.rst
docs/installation.rst
docs/make.bat
docs/readme.rst
docs/usage.rst
glogcli/__init__.py
glogcli/_version.py
glogcli/cli.py
glogcli/dateutils.py
glogcli/formats.py
glogcli/graylog_api.py
glogcli/input.py
glogcli/output.py
glogcli/utils.py
glogcli.egg-info/PKG-INFO
glogcli.egg-info/SOURCES.txt
glogcli.egg-info/dependency_links.txt
glogcli.egg-info/entry_points.txt
glogcli.egg-info/not-zip-safe
glogcli.egg-info/requires.txt
glogcli.egg-info/top_level.txt
tests/__init__.py
tests/test_api.py
tests/test_config.py
tests/test_date_utils.py
tests/test_formats.py
tests/test_input.py