Metadata-Version: 1.1
Name: glogcli
Version: 0.8.1
Summary: Graylog command line interface.
Home-page: https://github.com/globocom/glog-cli
Author: Sinval Vieira Mendes Neto
Author-email: sinvalneto01@gmail.com
License: Apache Software License 2.0
Download-URL: https://github.com/globocom/glog-cli/tarball/0.8.1
Keywords: glogcli
Platform: UNKNOWN
Classifier: Development Status :: 2 - Pre-Alpha
Classifier: Intended Audience :: Developers
Classifier: License :: OSI Approved :: Apache Software License
Classifier: Natural Language :: English
Classifier: Programming Language :: Python :: 2
Classifier: Programming Language :: Python :: 2.6
Classifier: Programming Language :: Python :: 2.7
